psnap/__init__.py
psnap/keyword_expander.py
psnap/state_tracker.py
psnap-0.7.2.data/scripts/psnap
psnap-0.7.2.data/scripts/psnap_example
psnap-0.7.2.data/scripts/psnap_example2
psnap-0.7.2.dist-info/LICENSE.txt
psnap-0.7.2.dist-info/METADATA
psnap-0.7.2.dist-info/WHEEL
psnap-0.7.2.dist-info/top_level.txt
psnap-0.7.2.dist-info/RECORD
