Metadata-Version: 2.1
Name: psnap
Version: 0.7.2
Summary: Snapshot script output to json and expand keywords in source file.
Home-page: https://github.com/hackermike/psnap
Author: Michael Frandsen
Author-email: wfrandsen@gmail.com
License: UNKNOWN
Platform: UNKNOWN
Classifier: Programming Language :: Python :: 2
Classifier: Programming Language :: Python :: 3
Classifier: Programming Language :: Python :: 2.7
Classifier: Programming Language :: Python :: 3.5
Classifier: Programming Language :: Python :: 3.6
Classifier: Programming Language :: Python :: 3.7
Classifier: Programming Language :: Python :: 3.8
Classifier: License :: OSI Approved :: MIT License
Classifier: Operating System :: OS Independent
